[{"prices": {"1": {"count": 38, "average": 594590, "median": 427956}, "all": {"count": 369, "average": 989854, "median": 846430}}, "month": "2009-7"}, {"prices": {"1": {"count": 42, "average": 415736, "median": 391288}, "all": {"count": 435, "average": 935887, "median": 839552}}, "month": "2009-8"}, {"prices": {"1": {"count": 20, "average": 431560, "median": 404571}, "all": {"count": 378, "average": 871959, "median": 814123}}, "month": "2009-9"}, {"prices": {"1": {"count": 27, "average": 513590, "median": 421873}, "all": {"count": 192, "average": 1011919, "median": 835786}}, "month": "2012-10"}, {"prices": {"1": {"count": 25, "average": 455008, "median": 418064}, "all": {"count": 134, "average": 983107, "median": 810244}}, "month": "2012-11"}, {"prices": {"1": {"count": 38, "average": 415334, "median": 387448}, "all": {"count": 130, "average": 909555, "median": 728219}}, "month": "2012-12"}, {"prices": {"1": {"count": 28, "average": 384486, "median": 407147}, "all": {"count": 94, "average": 940528, "median": 741963}}, "month": "2013-1"}, {"prices": {"1": {"count": 24, "average": 383878, "median": 388742}, "all": {"count": 220, "average": 971410, "median": 839988}}, "month": "2012-2"}, {"prices": {"1": {"count": 30, "average": 394949, "median": 405257}, "all": {"count": 306, "average": 968069, "median": 845461}}, "month": "2012-3"}, {"prices": {"1": {"count": 18, "average": 374303, "median": 354746}, "all": {"count": 180, "average": 902569, "median": 829701}}, "month": "2012-1"}, {"prices": {"1": {"count": 57, "average": 445027, "median": 424723}, "all": {"count": 298, "average": 907144, "median": 782400}}, "month": "2012-6"}, {"prices": {"1": {"count": 37, "average": 443260, "median": 425810}, "all": {"count": 187, "average": 987796, "median": 831968}}, "month": "2012-7"}, {"prices": {"1": {"count": 26, "average": 403095, "median": 411217}, "all": {"count": 183, "average": 921596, "median": 770366}}, "month": "2012-4"}, {"prices": {"1": {"count": 25, "average": 407024, "median": 421430}, "all": {"count": 186, "average": 938106, "median": 789585}}, "month": "2012-5"}, {"prices": {"1": {"count": 29, "average": 484668, "median": 442611}, "all": {"count": 162, "average": 988117, "median": 862597}}, "month": "2012-8"}, {"prices": {"1": {"count": 26, "average": 513659, "median": 449027}, "all": {"count": 197, "average": 1081115, "median": 872686}}, "month": "2012-9"}, {"prices": {"1": {"count": 6, "average": 329805, "median": 322406}, "all": {"count": 128, "average": 1262295, "median": 983936}}, "month": "2013-10"}, {"prices": {"1": {"count": 13, "average": 495086, "median": 475252}, "all": {"count": 86, "average": 1028796, "median": 953060}}, "month": "2013-4"}, {"prices": {"1": {"count": 10, "average": 366012, "median": 358892}, "all": {"count": 141, "average": 1234183, "median": 998041}}, "month": "2013-9"}, {"prices": {"1": {"count": 39, "average": 378445, "median": 358206}, "all": {"count": 321, "average": 887765, "median": 795351}}, "month": "2011-11"}, {"prices": {"1": {"count": 63, "average": 379072, "median": 369121}, "all": {"count": 433, "average": 900023, "median": 770178}}, "month": "2011-10"}, {"prices": {"1": {"count": 30, "average": 355358, "median": 341238}, "all": {"count": 302, "average": 933034, "median": 832206}}, "month": "2011-12"}, {"prices": {"1": {"count": 27, "average": 460419, "median": 441193}, "all": {"count": 131, "average": 1028465, "median": 838708}}, "month": "2013-7"}, {"prices": {"1": {"count": 47, "average": 351342, "median": 346612}, "all": {"count": 313, "average": 815255, "median": 751686}}, "month": "2010-12"}, {"prices": {"1": {"count": 12, "average": 435591, "median": 434252}, "all": {"count": 99, "average": 1215404, "median": 934396}}, "month": "2013-5"}, {"prices": {"1": {"count": 62, "average": 426678, "median": 429155}, "all": {"count": 524, "average": 927468, "median": 826182}}, "month": "2010-10"}, {"prices": {"1": {"count": 59, "average": 386696, "median": 366074}, "all": {"count": 395, "average": 862119, "median": 763011}}, "month": "2010-11"}, {"prices": {"1": {"count": 40, "average": 471200, "median": 436639}, "all": {"count": 369, "average": 919805, "median": 800470}}, "month": "2010-4"}, {"prices": {"1": {"count": 43, "average": 470559, "median": 436763}, "all": {"count": 508, "average": 942008, "median": 844678}}, "month": "2010-5"}, {"prices": {"1": {"count": 49, "average": 428357, "median": 357234}, "all": {"count": 398, "average": 877196, "median": 798743}}, "month": "2010-6"}, {"prices": {"1": {"count": 56, "average": 437063, "median": 397560}, "all": {"count": 427, "average": 868979, "median": 773699}}, "month": "2010-7"}, {"prices": {"1": {"count": 31, "average": 397332, "median": 433313}, "all": {"count": 313, "average": 836073, "median": 795525}}, "month": "2010-1"}, {"prices": {"1": {"count": 26, "average": 461184, "median": 430043}, "all": {"count": 224, "average": 891963, "median": 800851}}, "month": "2010-2"}, {"prices": {"1": {"count": 41, "average": 394209, "median": 395238}, "all": {"count": 314, "average": 936830, "median": 834970}}, "month": "2010-3"}, {"prices": {"1": {"count": 11, "average": 550599, "median": 548874}, "all": {"count": 105, "average": 1006110, "median": 895266}}, "month": "2013-3"}, {"prices": {"1": {"count": 35, "average": 425951, "median": 326860}, "all": {"count": 340, "average": 934058, "median": 816535}}, "month": "2010-8"}, {"prices": {"1": {"count": 43, "average": 421336, "median": 363104}, "all": {"count": 359, "average": 940153, "median": 810150}}, "month": "2010-9"}, {"prices": {"1": {"count": 22, "average": 509967, "median": 491824}, "all": {"count": 89, "average": 1081694, "median": 861479}}, "month": "2013-2"}, {"prices": {"1": {"count": 49, "average": 374106, "median": 380852}, "all": {"count": 289, "average": 938416, "median": 796299}}, "month": "2011-9"}, {"prices": {"1": {"count": 35, "average": 376176, "median": 410653}, "all": {"count": 258, "average": 937230, "median": 810701}}, "month": "2011-8"}, {"prices": {"1": {"count": 39, "average": 428667, "median": 399381}, "all": {"count": 523, "average": 857827, "median": 817505}}, "month": "2009-10"}, {"prices": {"1": {"count": 42, "average": 461304, "median": 405126}, "all": {"count": 367, "average": 848185, "median": 812432}}, "month": "2009-11"}, {"prices": {"1": {"count": 38, "average": 444871, "median": 439170}, "all": {"count": 330, "average": 871184, "median": 840919}}, "month": "2009-12"}, {"prices": {"1": {"count": 19, "average": 457792, "median": 459788}, "all": {"count": 161, "average": 1123944, "median": 976662}}, "month": "2013-8"}, {"prices": {"1": {"count": 30, "average": 349249, "median": 351559}, "all": {"count": 263, "average": 851619, "median": 758408}}, "month": "2011-1"}, {"prices": {"1": {"count": 29, "average": 493834, "median": 482231}, "all": {"count": 143, "average": 1062157, "median": 915628}}, "month": "2013-6"}, {"prices": {"1": {"count": 44, "average": 416123, "median": 396949}, "all": {"count": 266, "average": 876596, "median": 768439}}, "month": "2011-3"}, {"prices": {"1": {"count": 34, "average": 400216, "median": 380956}, "all": {"count": 234, "average": 883727, "median": 759821}}, "month": "2011-2"}, {"prices": {"1": {"count": 36, "average": 355165, "median": 335214}, "all": {"count": 327, "average": 854258, "median": 756617}}, "month": "2011-5"}, {"prices": {"1": {"count": 57, "average": 373528, "median": 362372}, "all": {"count": 390, "average": 871973, "median": 774251}}, "month": "2011-4"}, {"prices": {"1": {"count": 36, "average": 368107, "median": 396448}, "all": {"count": 326, "average": 908540, "median": 810346}}, "month": "2011-7"}, {"prices": {"1": {"count": 28, "average": 375916, "median": 358071}, "all": {"count": 284, "average": 867735, "median": 776056}}, "month": "2011-6"}]